boltznet/__init__.py
boltznet/boltznet_tf.py
boltznet/selftest.py
boltznet/test_module.py
boltznet/_internal/CONFIG.py
boltznet/_internal/aln.py
boltznet/_internal/base_data_type.py
boltznet/_internal/browser.py
boltznet/_internal/browser_util.py
boltznet/_internal/coverage.py
boltznet/_internal/factory.py
boltznet/_internal/fileDataType.py
boltznet/_internal/genomes.py
boltznet/_internal/model_create.py
boltznet/_internal/model_disect.py
boltznet/_internal/model_predict.py
boltznet/_internal/model_predict_create.py
boltznet/_internal/model_predict_models.py
boltznet/_internal/sequence.py
boltznet/_internal/tf_util.py
boltznet/_internal/util.py
boltznet/testdata/__init__.py
boltznet/testdata/ecoli.gff
boltznet/testdata/promoters.fa
boltznet-0.4.4.dist-info/licenses/LICENSE
boltznet-0.4.4.dist-info/METADATA
boltznet-0.4.4.dist-info/WHEEL
boltznet-0.4.4.dist-info/entry_points.txt
boltznet-0.4.4.dist-info/top_level.txt
boltznet-0.4.4.dist-info/RECORD
