Metadata-Version: 2.4
Name: boltznet
Version: 0.4.4
Summary: BoltzNet
Requires-Python: >=3.9
License-File: LICENSE
Requires-Dist: numpy<2,>=1.26
Requires-Dist: pandas<3,>=1.5
Requires-Dist: tensorflow<3,>=2.15
Requires-Dist: logomaker>=0.8
Requires-Dist: biopython
Requires-Dist: dna-features-viewer
Requires-Dist: seaborn
Requires-Dist: scipy
Requires-Dist: scikit-learn
Requires-Dist: setproctitle
Requires-Dist: bokeh==2.4.3
Requires-Dist: bcbio-gff
Requires-Dist: keras<3,>2.12.0
Requires-Dist: platformdirs
Dynamic: license-file
